{"characterType":"common","characterName":["モブA シック3","モブA シック3","路人A 高雅3","配角一 时髦3","모브A 시크3"],"firstName":["シック3","シック3","高雅3","时髦3","시크3"],"lastName":["モブA","モブA","路人A","配角一","모브A"],"nickname":[null,null,null,null,null],"sdAssetBundleName":"01006","seasonCostumeListMap":{"entries":{"season_1":{"entries":[{"characterId":1006,"basicSeasonId":1,"costumeType":"CASUAL","seasonCostumeType":"CASUAL_SPRING","sdAssetBundleName":"01006","live2dAssetBundleName":"1006","seasonType":"season_1"},{"characterId":1006,"basicSeasonId":1,"costumeType":"UNIFORM","seasonCostumeType":"UNIFORM_WINTER","sdAssetBundleName":"01006","live2dAssetBundleName":"1006","seasonType":"season_1"},{"characterId":1006,"basicSeasonId":2,"costumeType":"CASUAL","seasonCostumeType":"CASUAL_SPRING","sdAssetBundleName":"01006","live2dAssetBundleName":"1006","seasonType":"season_1"},{"characterId":1006,"basicSeasonId":2,"costumeType":"UNIFORM","seasonCostumeType":"UNIFORM_WINTER","sdAssetBundleName":"01006","live2dAssetBundleName":"1006","seasonType":"season_1"},{"characterId":1006,"basicSeasonId":3,"costumeType":"CASUAL","seasonCostumeType":"CASUAL_SPRING","sdAssetBundleName":"01006","live2dAssetBundleName":"1006","seasonType":"season_1"},{"characterId":1006,"basicSeasonId":3,"costumeType":"UNIFORM","seasonCostumeType":"UNIFORM_WINTER","sdAssetBundleName":"01006","live2dAssetBundleName":"1006","seasonType":"season_1"},{"characterId":1006,"basicSeasonId":4,"costumeType":"CASUAL","seasonCostumeType":"CASUAL_SPRING","sdAssetBundleName":"01006","live2dAssetBundleName":"1006","seasonType":"season_1"},{"characterId":1006,"basicSeasonId":4,"costumeType":"UNIFORM","seasonCostumeType":"UNIFORM_WINTER","sdAssetBundleName":"01006","live2dAssetBundleName":"1006","seasonType":"season_1"}]}}},"ruby":["もぶえーシック(C)","　","もぶえーシック(C)","配角一 时髦","모브A 시크(C)"]}