{"loginBonusType":"birthday","assetBundleName":["tae_2019","tae_2019","tae_2019","tae_2019","tae_2019"],"assetMap":{"entries":{"1":{"loginBonusId":170,"days":1,"resourceName":"no_icon","voiceId":"eventLoginBonus1"}}},"caption":["たえ誕生日","たえ誕生日","多惠生日","多惠生日","타에 생일 기념"],"publishedAt":["1575385200000","1607068800000","1607011200000","1638547200000","1607007600000"],"closedAt":["1575471599000","1607241599000","1607097599000","1638633599000","1607093999000"],"details":[[{"loginBonusId":170,"days":1,"resourceType":"star","quantity":50,"seq":1,"grantType":"direct"},{"loginBonusId":170,"days":1,"resourceType":"practice_ticket","resourceId":10,"quantity":1,"seq":2,"grantType":"direct"}],[{"loginBonusId":170,"days":1,"resourceType":"star","quantity":50,"seq":1,"grantType":"direct"},{"loginBonusId":170,"days":1,"resourceType":"practice_ticket","resourceId":10,"quantity":1,"seq":2,"grantType":"direct"}],[{"loginBonusId":170,"days":1,"resourceType":"star","quantity":50,"seq":1,"grantType":"direct"},{"loginBonusId":170,"days":1,"resourceType":"practice_ticket","resourceId":10,"quantity":1,"seq":2,"grantType":"direct"}],[{"loginBonusId":170,"days":1,"resourceType":"star","quantity":50,"voiceId":"","seq":1,"grantType":"direct"},{"loginBonusId":170,"days":1,"resourceType":"practice_ticket","resourceId":10,"quantity":1,"voiceId":"","seq":2,"grantType":"direct"}],[{"loginBonusId":170,"days":1,"resourceType":"star","quantity":50,"seq":1,"grantType":"direct"},{"loginBonusId":170,"days":1,"resourceType":"practice_ticket","resourceId":10,"quantity":1,"seq":2,"grantType":"direct"}]]}