{"loginBonusType":"birthday","assetBundleName":["chu2_2023","chu2_2023","chu2_2023","chu2_2023",null],"assetMap":{},"caption":["チュチュ誕生日記念","CHU² Birthday Celebration Present","CHU²生日紀念","CHU²生日纪念",null],"publishedAt":["1701874800000","1733558400000","1733500800000","1733500800000",null],"closedAt":["1701961199000","1733731199000","1733587199000","1733587199000",null],"details":[[{"loginBonusId":703,"days":1,"resourceType":"star","quantity":50,"seq":1,"grantType":"present"},{"loginBonusId":703,"days":1,"resourceType":"practice_ticket","resourceId":49,"quantity":1,"seq":2,"grantType":"present"}],[{"loginBonusId":703,"days":1,"resourceType":"star","quantity":50,"seq":1,"grantType":"present"},{"loginBonusId":703,"days":1,"resourceType":"practice_ticket","resourceId":49,"quantity":1,"seq":2,"grantType":"present"}],[{"loginBonusId":703,"days":1,"resourceType":"star","quantity":50,"seq":1,"grantType":"present"},{"loginBonusId":703,"days":1,"resourceType":"practice_ticket","resourceId":49,"quantity":1,"seq":2,"grantType":"present"}],[{"loginBonusId":703,"days":1,"resourceType":"star","quantity":50,"seq":1,"grantType":"present"},{"loginBonusId":703,"days":1,"resourceType":"practice_ticket","resourceId":49,"quantity":1,"seq":2,"grantType":"present"}],null]}