{"loginBonusType":"event","assetBundleName":["2024_half_aniv","2024_half_aniv","2024_half_aniv","2024_half_aniv",null],"assetMap":{},"caption":["「7.5周年記念メダル」プレゼントキャンペーン","7.5th Anniversary Medal Gift Campaign","「7.5週年紀念徽章」禮物特別活動","「悠悠春日徽章」特别礼物登录奖励活动",null],"publishedAt":["1728313200000","1762563600000","1746028800000","1745337600000",null],"closedAt":["1728399599000","1762649999000","1746115199000","1745423999000",null],"details":[[{"loginBonusId":894,"days":1,"resourceType":"limited_item","resourceId":40,"quantity":1000,"seq":1,"grantType":"direct"}],[{"loginBonusId":894,"days":1,"resourceType":"limited_item","resourceId":40,"quantity":1000,"seq":1,"grantType":"direct"}],[{"loginBonusId":894,"days":1,"resourceType":"limited_item","resourceId":40,"quantity":1000,"seq":1,"grantType":"direct"}],[{"loginBonusId":894,"days":1,"resourceType":"limited_item","resourceId":40,"quantity":1000,"seq":1,"grantType":"direct"}],null]}