{"loginBonusType":"event","assetBundleName":["8th_anniversary_countdown_0315",null,null,"8th_anniversary_countdown_0315",null],"assetMap":{},"caption":["8周年記念カウントダウンログインキャンペーン",null,null,"黄金周纪念倒计时登录奖励活动",null],"publishedAt":["1741964400000",null,null,"1758729600000",null],"closedAt":["1742025599000",null,null,"1758790799000",null],"details":[[{"loginBonusId":984,"days":1,"resourceType":"star","quantity":50,"seq":1,"grantType":"present"}],null,null,[{"loginBonusId":984,"days":1,"resourceType":"star","quantity":50,"seq":1,"grantType":"present"}],null]}