{"characterId":18,"rarity":2,"attribute":"powerful","levelLimit":30,"resourceSetName":"res018042","sdResourceName":"sd018042","episodes":{"entries":[{"episodeId":1793,"episodeType":"standard","situationId":1102,"scenarioId":"episode1102","appendPerformance":150,"appendTechnique":150,"appendVisual":150,"releaseLevel":1,"costs":{"entries":[{"resourceId":3,"resourceType":"item","quantity":100,"lbBonus":1}]},"rewards":{"entries":[{"resourceType":"star","quantity":25,"lbBonus":1}]},"title":["心色ブーケ","A Bouquet from the Heart","真心捧花","心色花束","마음 빛 부케"],"characterId":18},{"episodeId":1794,"episodeType":"memorial","situationId":1102,"scenarioId":"memorial1102","appendPerformance":300,"appendTechnique":300,"appendVisual":300,"releaseLevel":30,"costs":{"entries":[{"resourceId":3,"resourceType":"item","quantity":400,"lbBonus":1},{"resourceId":7,"resourceType":"item","quantity":150,"lbBonus":1}]},"rewards":{"entries":[{"resourceType":"star","quantity":50,"lbBonus":1}]},"title":["不揃いなピース","Differing Pieces","畸零的碎片","不完整的碎片","가지런하지 않은 피스"],"characterId":18}]},"costumeId":1043,"gachaText":[null,null,null,null,null],"prefix":["密やかな扶翼","Secret Assistance","暗中援助","无声的支持","은밀한 도움"],"releasedAt":["1610258400000","1637197200000","1623999600000","1642482000000","1610258400000"],"skillName":["クールダウン","Cool Down","Cool down","Cool Down","쿨 다운"],"skillId":5,"source":[{"event":{"138":{"point":"15000"}}},{"event":{"138":{"point":"11250"}}},{"event":{"138":{"point":"15000"}}},{"event":{"138":{"point":"11200"}}},{"event":{"138":{"point":"15000"}}}],"type":"event","stat":{"1":{"performance":2070,"technique":1890,"visual":1920},"2":{"performance":2126,"technique":1941,"visual":1972},"3":{"performance":2186,"technique":1995,"visual":2027},"4":{"performance":2249,"technique":2053,"visual":2086},"5":{"performance":2316,"technique":2114,"visual":2148},"6":{"performance":2387,"technique":2179,"visual":2214},"7":{"performance":2461,"technique":2247,"visual":2283},"8":{"performance":2539,"technique":2318,"visual":2355},"9":{"performance":2621,"technique":2393,"visual":2431},"10":{"performance":2707,"technique":2471,"visual":2510},"11":{"performance":2796,"technique":2552,"visual":2593},"12":{"performance":2889,"technique":2637,"visual":2679},"13":{"performance":2986,"technique":2725,"visual":2769},"14":{"performance":3086,"technique":2817,"visual":2862},"15":{"performance":3190,"technique":2912,"visual":2959},"16":{"performance":3298,"technique":3010,"visual":3059},"17":{"performance":3410,"technique":3112,"visual":3162},"18":{"performance":3525,"technique":3217,"visual":3269},"19":{"performance":3644,"technique":3326,"visual":3379},"20":{"performance":3767,"technique":3438,"visual":3493},"21":{"performance":3893,"technique":3553,"visual":3610},"22":{"performance":4023,"technique":3672,"visual":3731},"23":{"performance":4157,"technique":3794,"visual":3855},"24":{"performance":4294,"technique":3920,"visual":3983},"25":{"performance":4435,"technique":4049,"visual":4114},"26":{"performance":4580,"technique":4181,"visual":4248},"27":{"performance":4729,"technique":4317,"visual":4386},"28":{"performance":4881,"technique":4456,"visual":4527},"29":{"performance":5037,"technique":4598,"visual":4672},"30":{"performance":5197,"technique":4744,"visual":4820},"episodes":[{"performance":150,"technique":150,"visual":150},{"performance":300,"technique":300,"visual":300}]}}