{"characterId":33,"rarity":3,"attribute":"happy","levelLimit":40,"resourceSetName":"res033019","sdResourceName":"sd033019","episodes":{"entries":[{"episodeId":2521,"episodeType":"standard","situationId":1517,"scenarioId":"episode1517","appendPerformance":200,"appendTechnique":200,"appendVisual":200,"releaseLevel":1,"costs":{"entries":[{"resourceId":1,"resourceType":"item","quantity":300,"lbBonus":1},{"resourceId":5,"resourceType":"item","quantity":100,"lbBonus":1}]},"rewards":{"entries":[{"resourceType":"star","quantity":25,"lbBonus":1}]},"title":["背を預かって","Having Our Backs","把背後交給我","交予后背","등을 맡아"],"characterId":33},{"episodeId":2522,"episodeType":"memorial","situationId":1517,"scenarioId":"memorial1517","appendPerformance":500,"appendTechnique":500,"appendVisual":500,"releaseLevel":50,"costs":{"entries":[{"resourceId":1,"resourceType":"item","quantity":1800,"lbBonus":1},{"resourceId":5,"resourceType":"item","quantity":1200,"lbBonus":1},{"resourceId":9,"resourceType":"item","quantity":300,"lbBonus":1}]},"rewards":{"entries":[{"resourceType":"star","quantity":50,"lbBonus":1}]},"title":["響き合う情熱","Reverberating Passion","共鳴的熱情","共鸣的热情","서로 울리는 정열"],"characterId":33}]},"costumeId":1423,"gachaText":[null,null,null,null,null],"prefix":["律動隊　怒羅夢","RHYTHM SQUAD DRUMS","律動隊　怒羅夢","律动队 怒罗梦","선율대 드럼"],"releasedAt":["1653112800000","1677632400000","1667199600000","1675746000000","1653112800000"],"skillName":["やっぱRASはこうだよな","How RAS Oughta Be","RAS果然就要這樣","果然RAS就该这样","역시 RAS는 이렇지"],"skillId":6,"source":[{"event":{"187":{"point":"100000"}}},{"event":{"187":{"point":"75000"}}},{"event":{"187":{"point":"100000"}}},{"event":{"187":{"point":"100000"}}},{"event":{"187":{"point":"100000"}}}],"type":"event","stat":{"1":{"performance":3240,"technique":3096,"visual":2484},"2":{"performance":3283,"technique":3137,"visual":2517},"3":{"performance":3328,"technique":3180,"visual":2552},"4":{"performance":3375,"technique":3225,"visual":2588},"5":{"performance":3424,"technique":3272,"visual":2626},"6":{"performance":3476,"technique":3321,"visual":2666},"7":{"performance":3530,"technique":3372,"visual":2707},"8":{"performance":3586,"technique":3425,"visual":2750},"9":{"performance":3644,"technique":3481,"visual":2795},"10":{"performance":3704,"technique":3539,"visual":2841},"11":{"performance":3766,"technique":3599,"visual":2889},"12":{"performance":3831,"technique":3661,"visual":2938},"13":{"performance":3898,"technique":3725,"visual":2989},"14":{"performance":3967,"technique":3791,"visual":3042},"15":{"performance":4038,"technique":3859,"visual":3096},"16":{"performance":4111,"technique":3929,"visual":3152},"17":{"performance":4186,"technique":4001,"visual":3210},"18":{"performance":4263,"technique":4075,"visual":3269},"19":{"performance":4343,"technique":4151,"visual":3330},"20":{"performance":4425,"technique":4229,"visual":3393},"21":{"performance":4509,"technique":4309,"visual":3457},"22":{"performance":4595,"technique":4391,"visual":3523},"23":{"performance":4683,"technique":4475,"visual":3591},"24":{"performance":4773,"technique":4561,"visual":3660},"25":{"performance":4865,"technique":4649,"visual":3731},"26":{"performance":4960,"technique":4739,"visual":3804},"27":{"performance":5057,"technique":4832,"visual":3878},"28":{"performance":5156,"technique":4927,"visual":3954},"29":{"performance":5257,"technique":5024,"visual":4032},"30":{"performance":5360,"technique":5123,"visual":4111},"31":{"performance":5465,"technique":5224,"visual":4192},"32":{"performance":5573,"technique":5327,"visual":4274},"33":{"performance":5683,"technique":5432,"visual":4358},"34":{"performance":5795,"technique":5539,"visual":4444},"35":{"performance":5909,"technique":5648,"visual":4531},"36":{"performance":6025,"technique":5759,"visual":4620},"37":{"performance":6143,"technique":5872,"visual":4711},"38":{"performance":6263,"technique":5987,"visual":4803},"39":{"performance":6386,"technique":6104,"visual":4897},"40":{"performance":6511,"technique":6223,"visual":4993},"41":{"performance":6692,"technique":6396,"visual":5132},"42":{"performance":6906,"technique":6600,"visual":5296},"43":{"performance":7152,"technique":6835,"visual":5485},"44":{"performance":7431,"technique":7101,"visual":5699},"45":{"performance":7742,"technique":7398,"visual":5937},"46":{"performance":8086,"technique":7726,"visual":6200},"47":{"performance":8462,"technique":8085,"visual":6488},"48":{"performance":8870,"technique":8475,"visual":6801},"49":{"performance":9311,"technique":8896,"visual":7139},"50":{"performance":9784,"technique":9348,"visual":7502},"episodes":[{"performance":200,"technique":200,"visual":200},{"performance":500,"technique":500,"visual":500}],"training":{"levelLimit":10,"performance":300,"technique":300,"visual":300}}}